tieto_azure_apim_sdk/__init__.py
tieto_azure_apim_sdk/tieto_client.py
tieto_azure_apim_sdk-0.1.2.dist-info/METADATA
tieto_azure_apim_sdk-0.1.2.dist-info/WHEEL
tieto_azure_apim_sdk-0.1.2.dist-info/top_level.txt
tieto_azure_apim_sdk-0.1.2.dist-info/RECORD
