Metadata-Version: 2.4
Name: tieto_azure_apim_sdk
Version: 0.1.2
Summary: SDK for querying Azure OpenAI through Azure API Management Gateway.
Home-page: https://github.com/NaveenGandla/azure-apim-python-sdk
Author: Your Name
Classifier: Programming Language :: Python :: 3
Classifier: License :: OSI Approved :: MIT License
Requires-Python: >=3.7
Requires-Dist: requests
Dynamic: author
Dynamic: classifier
Dynamic: description
Dynamic: description-content-type
Dynamic: home-page
Dynamic: requires-dist
Dynamic: requires-python
Dynamic: summary
